{
  "snapshot_type": "cycle_3",
  "mission_id": "mission_ad5563a6",
  "stage": "CYCLE_END",
  "timestamp": "2026-02-01T17:32:31.435689",
  "snapshot_number": 2,
  "event_data": {
    "cycle_number": 3,
    "final": true,
    "final_report": {
      "summary": "Successfully implemented a production-ready conductor singleton pattern for the AtlasForge R&D engine. The solution prevents multiple conductor instances from running simultaneously, provides graceful takeover support for maintenance/upgrades, tracks collision events with rich metrics, and integrates a real-time status monitoring system into the dashboard. The implementation uses file-based locking with fcntl for atomicity, JSON-based lock files with heartbeat expiration for stale detection, and SIGTERM signaling for graceful handover. All 93 tests pass across unit, functional, adversarial, and property-based testing categories. The system is backward-compatible with legacy PID-only lock files and includes comprehensive CLI flags for operator control.",
      "all_files": [
        "/home/vader/AI-AtlasForge/workspace/ConductorTakeover/__init__.py",
        "/home/vader/AI-AtlasForge/workspace/ConductorTakeover/conductor_singleton.py",
        "/home/vader/AI-AtlasForge/workspace/ConductorTakeover/conductor_lock_metrics.py",
        "/home/vader/AI-AtlasForge/workspace/ConductorTakeover/conductor_integration.py",
        "/home/vader/AI-AtlasForge/workspace/ConductorTakeover/conductor_dashboard_api.py",
        "/home/vader/AI-AtlasForge/workspace/ConductorTakeover/conductor_ctl.py",
        "/home/vader/AI-AtlasForge/workspace/ConductorTakeover/tests/test_conductor_singleton.py",
        "/home/vader/AI-AtlasForge/workspace/ConductorTakeover/tests/functional_test_singleton.py",
        "/home/vader/AI-AtlasForge/workspace/ConductorTakeover/tests/adversarial_test_singleton.py",
        "/home/vader/AI-AtlasForge/workspace/ConductorTakeover/tests/property_test_singleton.py",
        "/home/vader/AI-AtlasForge/workspace/ConductorTakeover/artifacts/implementation_plan.md",
        "/home/vader/AI-AtlasForge/workspace/ConductorTakeover/artifacts/final_report.md",
        "/home/vader/AI-AtlasForge/workspace/ConductorTakeover/artifacts/test_results.md",
        "/home/vader/AI-AtlasForge/workspace/ConductorTakeover/research/analysis.md",
        "/home/vader/AI-AtlasForge/workspace/ConductorTakeover/research/research_findings.md",
        "/home/vader/AI-AtlasForge/workspace/ConductorTakeover/research/final_analysis.md",
        "/home/vader/AI-AtlasForge/atlasforge_conductor.py (modified)",
        "/home/vader/AI-AtlasForge/dashboard_v2.py (modified)"
      ],
      "key_achievements": [
        "Implemented robust file-based singleton pattern using fcntl locking with JSON metadata",
        "Created graceful takeover protocol with SIGTERM signaling and 30-second timeout",
        "Built comprehensive metrics tracking system with JSONL persistence for collision analysis",
        "Developed REST API endpoints for dashboard integration (status, metrics, collisions, takeover)",
        "Added CLI flags for operator control: --check-status, --takeover, --force-takeover",
        "Achieved 100% backward compatibility with legacy PID-only lock format",
        "Implemented automatic heartbeat mechanism (60s expiration, background thread updates)",
        "Passed rigorous multi-layer testing: 23 unit, 20 functional, 33 adversarial, 9 property tests",
        "Integrated seamlessly into existing atlasforge_conductor.py without breaking changes",
        "Added dashboard widget showing real-time conductor status, PID, mission, and collision count"
      ],
      "challenges_overcome": [
        "Race condition handling: Used fcntl.LOCK_EX | fcntl.LOCK_NB for atomic non-blocking acquisition",
        "Legacy format compatibility: Implemented dual-format parsing (JSON and PID-only) with lock_version field",
        "Stale lock detection: Combined PID liveness check (os.kill signal 0) with timestamp expiration",
        "Thread safety: Used threading.Lock for concurrent metrics writes (validated with 20-thread stress test)",
        "Signal handling: Installed SIGTERM/SIGINT handlers that allow current operation to complete before shutdown",
        "Heartbeat reliability: Background daemon thread with stop event for clean shutdown",
        "Dashboard integration: Created Flask blueprint that reads lock file directly without circular imports"
      ],
      "lessons_learned": [
        "fcntl.flock is the gold standard for Unix file locking - atomic, race-free, kernel-enforced",
        "JSON lock files provide rich metadata at no cost - hostname, timestamps, mission context enable better debugging",
        "Adversarial testing catches edge cases unit tests miss - malformed files, permission attacks, PID recycling",
        "Property-based testing validates invariants under random inputs - more confidence than finite test cases",
        "Legacy format support is critical for safe deployments - the running conductor should not break on upgrade",
        "SIGTERM + polling beats IPC complexity - simple, debuggable, no shared memory state to corrupt",
        "JSONL for metrics is perfect for append-only event logs - no database, no corruption risk, easy parsing",
        "Dashboard API should be stateless - read lock file on each request, never cache conductor state"
      ]
    }
  }
}