{
  "snapshot_type": "stage_planning",
  "mission_id": "mission_cf6b05d0",
  "stage": "PLANNING",
  "timestamp": "2026-01-25T15:37:47.257155",
  "snapshot_number": 0,
  "event_data": {
    "status": "plan_complete",
    "kb_learnings": [
      "Integration test suites should validate end-to-end flows (from mission_7dd4f18a deliverable)",
      "State machine testing requires explicit transition validation",
      "Mission state management architecture patterns (from inv_a2ce9bf3)"
    ],
    "steps_planned": 9
  }
}